po2lmo/__init__.py
po2lmo/cli.py
po2lmo/core.py
po2lmo-1.0.0.dist-info/licenses/LICENSE
po2lmo-1.0.0.dist-info/METADATA
po2lmo-1.0.0.dist-info/WHEEL
po2lmo-1.0.0.dist-info/entry_points.txt
po2lmo-1.0.0.dist-info/top_level.txt
po2lmo-1.0.0.dist-info/RECORD
