Metadata-Version: 2.4
Name: po2lmo
Version: 1.0.0
Summary: Convert GNU gettext PO files to Lua Machine Objects (LMO) binary format
Home-page: https://github.com/stevenjoezhang/po2lmo.py
Author: Shuqiao Zhang
Author-email: Shuqiao Zhang <stevenjoezhang@gmail.com>
Maintainer-email: Shuqiao Zhang <stevenjoezhang@gmail.com>
License: MIT
Project-URL: Homepage, https://github.com/stevenjoezhang/po2lmo.py
Project-URL: Repository, https://github.com/stevenjoezhang/po2lmo.py
Project-URL: Issues, https://github.com/stevenjoezhang/po2lmo.py/issues
Project-URL: Changelog, https://github.com/stevenjoezhang/po2lmo.py/blob/main/CHANGELOG.md
Keywords: gettext,po,lmo,lua,internationalization,localization,i18n,l10n
Classifier: Development Status :: 4 - Beta
Classifier: Intended Audience :: Developers
Classifier: Topic :: Software Development :: Internationalization
Classifier: Topic :: Software Development :: Localization
Classifier: License :: OSI Approved :: MIT License
Classifier: Programming Language :: Python :: 3
Classifier: Programming Language :: Python :: 3.7
Classifier: Programming Language :: Python :: 3.8
Classifier: Programming Language :: Python :: 3.9
Classifier: Programming Language :: Python :: 3.10
Classifier: Programming Language :: Python :: 3.11
Classifier: Programming Language :: Python :: 3.12
Classifier: Operating System :: OS Independent
Requires-Python: >=3.7
License-File: LICENSE
Dynamic: author
Dynamic: home-page
Dynamic: license-file
Dynamic: requires-python
